evidence_api/__init__.py
evidence_api/api.py
evidence_api/binaryblob.py
evidence_api/ccel.py
evidence_api/ccreport.py
evidence_api/eventlog.py
evidence_api/imr.py
evidence_api/tcg.py
evidence_api/tcgcel.py
evidence_api/tdx/__init__.py
evidence_api/tdx/common.py
evidence_api/tdx/quote.py
evidence_api/tdx/report.py
evidence_api/tdx/rtmr.py
evidence_api/tpm/pcr.py
evidence_api/tpm/quote.py
evidence_api-0.5.0.dist-info/METADATA
evidence_api-0.5.0.dist-info/WHEEL
evidence_api-0.5.0.dist-info/top_level.txt
evidence_api-0.5.0.dist-info/RECORD
