Metadata-Version: 2.1
Name: evidence_api
Version: 0.5.0
Summary: Evidence API Base SDK
Author-email: "Lu, Ken" <ken.lu@intel.com>, "Zhang, Wenhui" <wenhui.zhang@bytedance.com>
License: Apache Software License
Project-URL: Homepage, https://github.com/cc-api/evidence-api
Project-URL: Bug Tracker, https://github.com/cc-api/evidence-api/issues
Classifier: Programming Language :: Python :: 3
Classifier: License :: OSI Approved :: Apache Software License
Classifier: Operating System :: POSIX :: Linux
Requires-Python: >=3.6
